README.txt
setup.cfg
setup.py
MP3AlbumCheck.egg-info/PKG-INFO
MP3AlbumCheck.egg-info/SOURCES.txt
MP3AlbumCheck.egg-info/dependency_links.txt
MP3AlbumCheck.egg-info/entry_points.txt
MP3AlbumCheck.egg-info/not-zip-safe
MP3AlbumCheck.egg-info/top_level.txt
mp3albumcheck/__init__.py
mp3albumcheck/cddb.py
mp3albumcheck/cli.py