Metadata-Version: 1.0
Name: MP3AlbumCheck
Version: 1
Summary: Checks a directory of MP3s to ensure it matches its CD equivilent
Home-page: http://terrarum.net/mp3albumcheck.html
Author: Joe Topjian
Author-email: joe@terrarum.net
License: BSD
Keywords: mp3 album freedb cddb eyed3
Platform: UNKNOWN
Classifier: Environment :: Console
Classifier: Topic :: Multimedia :: Sound/Audio
Classifier: Topic :: Multimedia :: Sound/Audio :: Analysis
